pygsm/__init__.py
pygsm/backup.py
pygsm/cli.py
pygsm/config.py
pygsm/monitor.py
pygsm/server.py
pygsm/steamcmd.py
pygsm/servers/arma3/__init__.py
pygsm/servers/arma3/arma3.py
cligsm-0.1.6.dist-info/METADATA
cligsm-0.1.6.dist-info/WHEEL
cligsm-0.1.6.dist-info/entry_points.txt
cligsm-0.1.6.dist-info/RECORD
