Metadata-Version: 2.4
Name: cligsm
Version: 0.1.6
Summary: A user-friendly CLI alternative to LinuxGSM for game server management
Project-URL: Homepage, https://github.com/andrewwade/pygsm
Project-URL: Issues, https://github.com/andrewwade/pygsm/issues
Author: Andrew Wade
License: MIT
Classifier: License :: OSI Approved :: MIT License
Classifier: Operating System :: OS Independent
Classifier: Programming Language :: Python :: 3
Requires-Python: >=3.8
Requires-Dist: click>=8.0.0
Requires-Dist: psutil>=5.9.0
Requires-Dist: requests>=2.28.0
Requires-Dist: rich>=10.0.0
Provides-Extra: all
Requires-Dist: build>=0.10.0; extra == 'all'
Requires-Dist: bump2version>=1.0.0; extra == 'all'
Requires-Dist: click>=8.0.0; extra == 'all'
Requires-Dist: psutil>=5.9.0; extra == 'all'
Requires-Dist: pytest>=7.0.0; extra == 'all'
Requires-Dist: requests>=2.28.0; extra == 'all'
Requires-Dist: rich>=10.0.0; extra == 'all'
Requires-Dist: twine>=4.0.0; extra == 'all'
Provides-Extra: dev
Requires-Dist: build>=0.10.0; extra == 'dev'
Requires-Dist: bump2version>=1.0.0; extra == 'dev'
Requires-Dist: pytest>=7.0.0; extra == 'dev'
Requires-Dist: twine>=4.0.0; extra == 'dev'
